blosc2_btune/__init__.py
blosc2_btune/libblosc2_btune.dll
include/btune.h
blosc2_btune-1.2.1.dist-info/METADATA
blosc2_btune-1.2.1.dist-info/WHEEL
blosc2_btune-1.2.1.dist-info/licenses/LICENSE.txt
blosc2_btune-1.2.1.dist-info/RECORD
