Metadata-Version: 2.2
Name: blosc2_btune
Version: 1.2.1
Summary: Btune plugin for Blosc2. Automatically choose the best codec/filter for your data.
Keywords: plugin,blosc2
Author-Email: ironArray SLU <contact@ironarray.io>
License: GNU Affero General Public License version 3
Classifier: Programming Language :: Python :: 3
Classifier: Programming Language :: C
Classifier: Programming Language :: C++
Classifier: Development Status :: 5 - Production/Stable
Classifier: Intended Audience :: Developers
Classifier: License :: OSI Approved :: GNU Affero General Public License v3 or later (AGPLv3+)
Classifier: Topic :: Software Development :: Libraries :: Python Modules
Classifier: Operating System :: Microsoft :: Windows
Classifier: Operating System :: Unix
Requires-Dist: blosc2
